bayesnf/__init__.py
bayesnf/inference.py
bayesnf/models.py
bayesnf/spatiotemporal.py
bayesnf-0.1.3.dist-info/LICENSE
bayesnf-0.1.3.dist-info/WHEEL
bayesnf-0.1.3.dist-info/METADATA
bayesnf-0.1.3.dist-info/RECORD
