Metadata-Version: 2.1
Name: bayesnf
Version: 0.1.3
Summary: Scalable spatiotemporal prediction with Bayesian neural fields
Keywords: 
Author-email: bayesnf authors <bayesnf@google.com>
Requires-Python: >=3.9
Classifier: License :: OSI Approved :: Apache Software License
Classifier: Intended Audience :: Science/Research
Requires-Dist: flax
Requires-Dist: jax>=0.4.6
Requires-Dist: jaxtyping
Requires-Dist: numpy
Requires-Dist: optax
Requires-Dist: pandas
Requires-Dist: tensorflow-probability[jax]>=0.19.0
Requires-Dist: pytest ; extra == "dev"
Requires-Dist: pytest-xdist ; extra == "dev"
Requires-Dist: pylint>=2.6.0 ; extra == "dev"
Requires-Dist: pyink ; extra == "dev"
Requires-Dist: tqdm ; extra == "dev"
Requires-Dist: mkdocs==1.5.3 ; extra == "docs"
Requires-Dist: mkdocstrings[python]>=0.18 ; extra == "docs"
Requires-Dist: mkdocs-material==8.2.6 ; extra == "docs"
Requires-Dist: pymdown-extensions==9.4 ; extra == "docs"
Requires-Dist: mknotebooks==0.7.1 ; extra == "docs"
Requires-Dist: pytkdocs_tweaks==0.0.8 ; extra == "docs"
Requires-Dist: jinja2==3.0.3 ; extra == "docs"
Requires-Dist: nbconvert==6.5.0 ; extra == "docs"
Requires-Dist: nbformat==5.4.0 ; extra == "docs"
Requires-Dist: pygments==2.14.0 ; extra == "docs"
Project-URL: changelog, https://github.com/google/bayesnf/blob/main/CHANGELOG.md
Project-URL: homepage, https://github.com/google/bayesnf
Project-URL: repository, https://github.com/google/bayesnf
Provides-Extra: dev
Provides-Extra: docs
